LICENSE
MANIFEST.in
README
setup.py
contrib/completion.zsh
notsio/__init__.py
notsio/__main__.py
notsio/cli.py
notsio/client.py
notsio/utils.py
notsio.egg-info/PKG-INFO
notsio.egg-info/SOURCES.txt
notsio.egg-info/dependency_links.txt
notsio.egg-info/entry_points.txt
notsio.egg-info/requires.txt
notsio.egg-info/top_level.txt