Metadata-Version: 1.1
Name: notsio
Version: 0.6.0
Summary: cli - notsio note and bookmark command line utility
Home-page: http://nrocco.github.io
Author: Nico Di Rocco
Author-email: dirocco.nico@gmail.com
License: UNKNOWN
Platform: UNKNOWN
Classifier: Development Status :: 5 - Production/Stable
Classifier: Environment :: Console
Classifier: Operating System :: Unix
Classifier: Programming Language :: Python
Classifier: Programming Language :: Python :: 3
Classifier: Programming Language :: Python :: 3.2
Classifier: Programming Language :: Python :: 3.3
Classifier: Programming Language :: Python :: 3.4
Classifier: Topic :: Utilities
